MAGINE-0.0.15.data/scripts/create_template_project
MAGINE-0.0.15.data/scripts/download_databases.py
magine/__init__.py
magine/copy_sample_dbs.py
magine/logging.py
magine/data/__init__.py
magine/data/base.py
magine/data/experimental_data.py
magine/data/storage.py
magine/data/tools.py
magine/enrichment/__init__.py
magine/enrichment/_valid_enricher_libs.txt
magine/enrichment/enrichment_result.py
magine/enrichment/enrichr.py
magine/enrichment/deprecated/__init__.py
magine/enrichment/deprecated/ontology_analysis.py
magine/enrichment/deprecated/ontology_tools.py
magine/enrichment/deprecated/test_ontology_tools.py
magine/enrichment/deprecated/databases/__init__.py
magine/enrichment/deprecated/databases/gene_ontology.py
magine/examples/__init__.py
magine/examples/cisplatin/__init__.py
magine/examples/cisplatin/compare_networks.py
magine/examples/cisplatin/exp_data.py
magine/examples/cisplatin/generate_network.py
magine/examples/cisplatin/run_enrichment_analysis.py
magine/examples/drug_comparison/__init__.py
magine/html_templates/__init__.py
magine/html_templates/html_tools.py
magine/html_templates/templates/base.html
magine/html_templates/templates/filter_table.html
magine/html_templates/templates/main_view.html
magine/html_templates/templates/plotly_template.html
magine/html_templates/templates/single_table_view.html
magine/html_templates/templates/subgraph.html
magine/html_templates/templates/subgraph_2.html
magine/html_templates/templates/subgraph_3.html
magine/html_templates/templates/workflow_template.html
magine/mappings/__init__.py
magine/mappings/chemical_mapper.py
magine/mappings/gene_mapper.py
magine/mappings/maps.py
magine/mappings/databases/__init__.py
magine/mappings/databases/download_libraries.py
magine/mappings/databases/pubchem.py
magine/mappings/databases/update.py
magine/networks/__init__.py
magine/networks/annotated_set.py
magine/networks/combine_species_networks.py
magine/networks/create_bg.py
magine/networks/dev_tools.py
magine/networks/exporters.py
MAGINE-0.0.15.dist-info/LICENSE
MAGINE-0.0.15.dist-info/METADATA
MAGINE-0.0.15.dist-info/WHEEL
MAGINE-0.0.15.dist-info/entry_points.txt
MAGINE-0.0.15.dist-info/top_level.txt
MAGINE-0.0.15.dist-info/RECORD
