Metadata-Version: 2.1
Name: MAGINE
Version: 0.0.15
Summary: Package to analyze biological data.
Home-page: https://github.com/LoLab-VU/Magine
Author: James Pino
Author-email: james.ch.pino@gmail.com
License: UNKNOWN
Keywords: biological networks,biological pathways,enrichment analysis,network analysis,visualization,multi-omics,rnaseq,proteomics,metabolomics
Platform: UNKNOWN
Classifier: Development Status :: 3 - Alpha
Classifier: Operating System :: OS Independent
Classifier: Programming Language :: Python :: 2
Classifier: Programming Language :: Python :: 3
Classifier: Intended Audience :: Science/Research
Requires-Dist: bioservices
Requires-Dist: defusedxml
Requires-Dist: ipywidgets
Requires-Dist: jinja2
Requires-Dist: jupyter
Requires-Dist: matplotlib
Requires-Dist: matplotlib-venn
Requires-Dist: networkx (<2.4,>=2.1)
Requires-Dist: numpy
Requires-Dist: pandas
Requires-Dist: pathos
Requires-Dist: plotly (==2.7)
Requires-Dist: py2cytoscape
Requires-Dist: pydot
Requires-Dist: pydotplus
Requires-Dist: requests
Requires-Dist: scipy
Requires-Dist: seaborn
Requires-Dist: sortedcontainers
Requires-Dist: statsmodels
Requires-Dist: wordcloud
Requires-Dist: xlrd
Provides-Extra: test
Requires-Dist: coverage ; extra == 'test'
